dp_fusion_lib/__init__.py
dp_fusion_lib/_version.py
dp_fusion_lib/core.py
dp_fusion_lib/epsilon.py
dp_fusion_lib/tagger.py
dp_fusion_lib/utils.py
dp_fusion_lib-0.1.0.dist-info/licenses/LICENSE
dp_fusion_lib-0.1.0.dist-info/licenses/LICENSE-COMMERCIAL.md
dp_fusion_lib-0.1.0.dist-info/METADATA
dp_fusion_lib-0.1.0.dist-info/WHEEL
dp_fusion_lib-0.1.0.dist-info/top_level.txt
dp_fusion_lib-0.1.0.dist-info/RECORD
