Metadata-Version: 2.4
Name: dp-fusion-lib
Version: 0.1.0
Summary: Token-Level Differentially Private Inference for Large Language Models
Author-email: Rushil Thareja <rushil.thareja@mbzuai.ac.ae>
License: DP-Fusion-Lib Non-Commercial License
Project-URL: Homepage, https://github.com/rushil-thareja/dp-fusion-lib
Project-URL: Documentation, https://rushil-thareja.github.io/dp-fusion-lib
Project-URL: Repository, https://github.com/rushil-thareja/dp-fusion-lib
Project-URL: Issues, https://github.com/rushil-thareja/dp-fusion-lib/issues
Project-URL: Paper, https://arxiv.org/abs/2507.04531
Keywords: differential-privacy,llm,text-generation,privacy,nlp,renyi-divergence
Classifier: Development Status :: 4 - Beta
Classifier: Intended Audience :: Developers
Classifier: Intended Audience :: Science/Research
Classifier: License :: Other/Proprietary License
Classifier: Programming Language :: Python :: 3
Classifier: Programming Language :: Python :: 3.8
Classifier: Programming Language :: Python :: 3.9
Classifier: Programming Language :: Python :: 3.10
Classifier: Programming Language :: Python :: 3.11
Classifier: Topic :: Scientific/Engineering :: Artificial Intelligence
Classifier: Topic :: Security
Requires-Python: >=3.8
License-File: LICENSE
License-File: LICENSE-COMMERCIAL.md
Requires-Dist: torch>=2.0.0
Requires-Dist: transformers>=4.25.0
Requires-Dist: accelerate>=0.20.0
Requires-Dist: requests>=2.25.0
Provides-Extra: dev
Requires-Dist: pytest>=7.0.0; extra == "dev"
Requires-Dist: pytest-cov>=4.0.0; extra == "dev"
Requires-Dist: black>=23.0.0; extra == "dev"
Requires-Dist: ruff>=0.1.0; extra == "dev"
Requires-Dist: pre-commit>=3.0.0; extra == "dev"
Provides-Extra: docs
Requires-Dist: mkdocs>=1.5.0; extra == "docs"
Requires-Dist: mkdocs-material>=9.0.0; extra == "docs"
Requires-Dist: mkdocstrings[python]>=0.24.0; extra == "docs"
Dynamic: license-file
